LICENSE
MANIFEST.in
Makefile
README
README.md
setup.cfg
setup.py
tox.ini
test/__init__.py
test/test_standard.py
unstdlib/__init__.py
unstdlib/formencode.py
unstdlib/html.py
unstdlib/six.py
unstdlib/sqlalchemy.py
unstdlib.egg-info/PKG-INFO
unstdlib.egg-info/SOURCES.txt
unstdlib.egg-info/dependency_links.txt
unstdlib.egg-info/top_level.txt
unstdlib/standard/__init__.py
unstdlib/standard/collections_.py
unstdlib/standard/contextlib_.py
unstdlib/standard/datetime_.py
unstdlib/standard/dict_.py
unstdlib/standard/exception_.py
unstdlib/standard/functools_.py
unstdlib/standard/list_.py
unstdlib/standard/os_.py
unstdlib/standard/random_.py
unstdlib/standard/string_.py
unstdlib/standard/type_.py