Metadata-Version: 1.0
Name: unstdlib
Version: 1.7.2
Summary: Unstandard Python library of useful and highly-reusable functions
Home-page: https://github.com/shazow/unstdlib.py
Author: Andrey Petrov
Author-email: andrey.petrov@shazow.net
License: MIT
Platform: any
